rubin/repertoire/__init__.py
rubin/repertoire/_builder.py
rubin/repertoire/_client.py
rubin/repertoire/_config.py
rubin/repertoire/_dependencies.py
rubin/repertoire/_exceptions.py
rubin/repertoire/_mock.py
rubin/repertoire/_models.py
rubin/repertoire/py.typed
rubin_repertoire-0.8.0.dist-info/licenses/LICENSE
rubin_repertoire-0.8.0.dist-info/METADATA
rubin_repertoire-0.8.0.dist-info/WHEEL
rubin_repertoire-0.8.0.dist-info/top_level.txt
rubin_repertoire-0.8.0.dist-info/RECORD
